LICENSE
pypdbio.py
setup.py
pypdbio.egg-info/PKG-INFO
pypdbio.egg-info/SOURCES.txt
pypdbio.egg-info/dependency_links.txt
pypdbio.egg-info/requires.txt
pypdbio.egg-info/top_level.txt
test/test.py