Metadata-Version: 2.4
Name: pypdbio
Version: 0.0.2
Summary: A package for downloading/reading/writing pdb file
Home-page: 
Author: Xiaoyang Liu
Author-email: liuxiaoyang_Q@outlook.com
License: MIT
License-File: LICENSE
Requires-Dist: requests
Dynamic: author
Dynamic: author-email
Dynamic: license
Dynamic: license-file
Dynamic: requires-dist
Dynamic: summary
